threadlocal_aws/__init__.py
threadlocal_aws/clients.py
threadlocal_aws/pep562.py
threadlocal_aws/resources.py
threadlocal_aws-0.11.dist-info/METADATA
threadlocal_aws-0.11.dist-info/WHEEL
threadlocal_aws-0.11.dist-info/top_level.txt
threadlocal_aws-0.11.dist-info/zip-safe
threadlocal_aws-0.11.dist-info/RECORD
