Metadata-Version: 2.1
Name: threadlocal-aws
Version: 0.11
Summary: Library to access threadlocal aws clients and resources
Home-page: http://github.com/NitorCreations/threadlocal-aws
Author: Pasi Niemi
Author-email: pasi.niemi@nitor.com
License: Apache 2.0
Download-URL: https://github.com/NitorCreations/threadlocal-aws/tarball/0.11
Platform: UNKNOWN
Requires-Dist: boto3
Requires-Dist: requests
Requires-Dist: urllib3
